dblit/__init__.py
dblit/app.py
dblit/base.py
dblit/item.py
dblit/job.py
dblit/label.py
dblit/label_set.py
dblit/user.py
dblit-0.0.3.dist-info/METADATA
dblit-0.0.3.dist-info/WHEEL
dblit-0.0.3.dist-info/top_level.txt
dblit-0.0.3.dist-info/RECORD
